ddpw/__init__.py
ddpw/functional.py
ddpw/io.py
ddpw/platform.py
ddpw/wrapper.py
ddpw-5.5.1.dist-info/licenses/LICENCE
ddpw-5.5.1.dist-info/WHEEL
ddpw-5.5.1.dist-info/METADATA
ddpw-5.5.1.dist-info/RECORD
