Metadata-Version: 2.4
Name: ddpw
Version: 5.5.1
Summary: A lightweight wrapper that scaffolds PyTorch's Distributed (Data) Parallel.
Keywords: pytorch,distributed compute
Author: Sujal Vijayaraghavan
License-Expression: BSD-3-Clause
License-File: LICENCE
Classifier: Programming Language :: Python
Requires-Dist: submitit>=1.5.3
Requires-Dist: torch>=2.8.0
Maintainer: Sujal Vijayaraghavan
Requires-Python: >=3.13
Project-URL: Documentation, https://ddpw.projects.sujal.tv
Project-URL: Homepage, https://ddpw.projects.sujal.tv
Project-URL: Repository, https://github.com/sujaltv/ddpw
